{
	"name": "Post game layout 7",
	"layers": [
		{
			"name": "Layer 0",
			"overriden": 0,
			"instances": [
				{
					"type": "TiledBackground3",
					"properties": {
						"initially-visible": true,
						"origin": "top-left",
						"wrap-horizontal": "repeat",
						"wrap-vertical": "repeat",
						"image-offset-x": 0,
						"image-offset-y": 0,
						"image-scale-x": 1,
						"image-scale-y": 1,
						"image-angle": 0
					},
					"uid": 69,
					"instanceVariables": {},
					"behaviors": {},
					"world": {
						"x": 0,
						"y": 0,
						"width": 1600,
						"height": 1200,
						"originX": 0,
						"originY": 0,
						"color": [
							1,
							1,
							1,
							1
						],
						"angle": 0,
						"zElevation": 0
					}
				},
				{
					"type": "Justinjobstext",
					"properties": {
						"text": "",
						"enable-bbcode": true,
						"font": "Arial",
						"size": 67,
						"line-height": 0,
						"bold": false,
						"italic": false,
						"color": [
							1,
							1,
							1,
							1
						],
						"horizontal-alignment": "left",
						"vertical-alignment": "top",
						"wrapping": "word",
						"initially-visible": true,
						"origin": "top-left"
					},
					"uid": 79,
					"instanceVariables": {},
					"behaviors": {},
					"world": {
						"x": 107,
						"y": 233,
						"width": 1413,
						"height": 557,
						"originX": 0,
						"originY": 0,
						"color": [
							1,
							1,
							1,
							1
						],
						"angle": 0,
						"zElevation": 0
					}
				},
				{
					"type": "Text9",
					"properties": {
						"text": "Justin Faircloth\nLimestone Correctional Facility \nRecorded via prison telephone",
						"enable-bbcode": true,
						"font": "Arial",
						"size": 30,
						"line-height": 0,
						"bold": false,
						"italic": false,
						"color": [
							1,
							1,
							1,
							1
						],
						"horizontal-alignment": "left",
						"vertical-alignment": "top",
						"wrapping": "word",
						"initially-visible": true,
						"origin": "top-left"
					},
					"uid": 80,
					"instanceVariables": {},
					"behaviors": {},
					"world": {
						"x": 535,
						"y": 929,
						"width": 1120,
						"height": 206,
						"originX": 0,
						"originY": 0,
						"color": [
							1,
							1,
							1,
							1
						],
						"angle": 0,
						"zElevation": 0
					}
				},
				{
					"type": "Sprite7",
					"properties": {
						"initially-visible": true,
						"initial-animation": "Animation 1",
						"initial-frame": 0,
						"enable-collisions": true,
						"live-preview": false
					},
					"uid": 81,
					"instanceVariables": {},
					"behaviors": {},
					"world": {
						"x": 180,
						"y": 995,
						"width": 175.8929810991497,
						"height": 232.58576013110704,
						"originX": 0.5,
						"originY": 0.5,
						"color": [
							1,
							1,
							1,
							1
						],
						"angle": 0,
						"zElevation": 0
					}
				},
				{
					"type": "Speaker",
					"properties": {
						"initially-visible": true,
						"initial-animation": "Animation 1",
						"initial-frame": 0,
						"enable-collisions": true,
						"live-preview": false
					},
					"uid": 82,
					"instanceVariables": {},
					"behaviors": {},
					"world": {
						"x": 420,
						"y": 995,
						"width": 121.17463147794982,
						"height": 123.1611008464408,
						"originX": 0.5,
						"originY": 0.5,
						"color": [
							1,
							1,
							1,
							1
						],
						"angle": 0,
						"zElevation": 0
					}
				},
				{
					"type": "Securustext",
					"properties": {
						"text": "",
						"enable-bbcode": true,
						"font": "Courier New",
						"size": 48,
						"line-height": 0,
						"bold": false,
						"italic": true,
						"color": [
							0.28627450980392155,
							0.9921568627450981,
							0.30980392156862746,
							1
						],
						"horizontal-alignment": "left",
						"vertical-alignment": "top",
						"wrapping": "word",
						"initially-visible": true,
						"origin": "top-left"
					},
					"uid": 83,
					"instanceVariables": {},
					"behaviors": {},
					"world": {
						"x": 107,
						"y": 25,
						"width": 1392,
						"height": 287,
						"originX": 0,
						"originY": 0,
						"color": [
							1,
							1,
							1,
							1
						],
						"angle": 0,
						"zElevation": 0
					}
				}
			],
			"sid": 598805866667522,
			"effectTypes": [],
			"isInitiallyVisible": true,
			"color": [
				1,
				1,
				1,
				1
			],
			"backgroundColor": [
				1,
				1,
				1,
				1
			],
			"isTransparent": false,
			"parallaxX": 1,
			"parallaxY": 1,
			"scaleRate": 1,
			"forceOwnTexture": false,
			"useRenderCells": false,
			"blendMode": "normal",
			"global": false
		},
		{
			"name": "Back-Forward Layer",
			"overriden": 1,
			"instances": [],
			"sid": 379822446401571,
			"effectTypes": [],
			"isInitiallyVisible": true,
			"color": [
				1,
				1,
				1,
				1
			],
			"backgroundColor": [
				1,
				1,
				1,
				1
			],
			"isTransparent": true,
			"parallaxX": 1,
			"parallaxY": 1,
			"scaleRate": 1,
			"forceOwnTexture": false,
			"useRenderCells": false,
			"blendMode": "normal",
			"global": false
		}
	],
	"sid": 819455379547334,
	"nonworld-instances": [],
	"effectTypes": [],
	"width": 1600,
	"height": 1200,
	"unboundedScrolling": false,
	"eventSheet": "Post game sheet 7"
}